cloud_annotations/__init__.py
cloud_annotations-0.0.5.dist-info/LICENSE
cloud_annotations-0.0.5.dist-info/METADATA
cloud_annotations-0.0.5.dist-info/WHEEL
cloud_annotations-0.0.5.dist-info/top_level.txt
cloud_annotations-0.0.5.dist-info/RECORD
