Metadata-Version: 2.1
Name: cloud-annotations
Version: 0.0.5
Summary: The Cloud Annotations python SDK
Home-page: https://github.com/cloud-annotations/python-sdk
Author: Nick Bourdakos
Author-email: bourdakos1@gmail.com
License: UNKNOWN
Platform: UNKNOWN
Classifier: Programming Language :: Python :: 3
Classifier: License :: OSI Approved :: MIT License
Classifier: Operating System :: OS Independent
Requires-Python: >=3.6
